pygifconvt_KANG/Converter.py
pygifconvt_KANG/__init__.py
pygifconvt_KANG-1.0.0.dist-info/LICENSE
pygifconvt_KANG-1.0.0.dist-info/METADATA
pygifconvt_KANG-1.0.0.dist-info/WHEEL
pygifconvt_KANG-1.0.0.dist-info/top_level.txt
pygifconvt_KANG-1.0.0.dist-info/RECORD
