Metadata-Version: 2.1
Name: pygifconvt_KANG
Version: 1.0.0
Summary: Test package for distribution
Home-page: 
Download-URL: 
Author: Eunki7
Author-email: ktt0570@gmail.com
Keywords: GIFCONVERTER,gifconverter
Classifier: Programming Language :: Python :: 3
Classifier: License :: OSI Approved :: MIT License
Classifier: Operating System :: OS Independent
Requires-Python: >=3
License-File: LICENSE
Requires-Dist: pillow
